freecaptcha/__init__.py
freecaptcha/bypass.py
freecaptcha-1.2.0.dist-info/METADATA
freecaptcha-1.2.0.dist-info/WHEEL
freecaptcha-1.2.0.dist-info/RECORD
