Metadata-Version: 2.4
Name: freecaptcha
Version: 1.2.0
Summary: A simple and free reCAPTCHA V3 bypass.
Author: task0001
Requires-Python: >=3.12
Requires-Dist: yarl>=1.18.3
